{"id": "brk1665702777359", "title": "Service Stored Procedures on Microsoft SQL Server", "breadcrumbs": ["DBMS Support", "Database Connectors", "Microsoft SQL Server", "Stored Procedures on Microsoft SQL Server", "Service Stored Procedures on Microsoft SQL Server"], "url": "https://docs.rocketsoftware.com/de-DE/bundle/uniface_104/page/brk1665702777359.html", "html": "<html><body><header class=\"zDocsTopicPageHead\"><h1 class=\"css-g931ng\">Service Stored Procedures on Microsoft SQL Server</h1><div class=\"zDocsTopicActions\" role=\"list\"><div class=\"zDocsBundlePagination\" data-testid=\"next-prev-container\" role=\"listitem\"><div class=\"zDocsPrevTopicButton zDocsPrevTopicButton\"><span class=\"\"><a aria-label=\"Previous:    Stored Procedures on Microsoft SQL Server \" class=\"\" data-tooltip-content=\"Previous:    Stored Procedures on Microsoft SQL Server \" data-tooltip-id=\"zDocsTopicActionsTooltip\" data-tooltip-open=\"false\" href=\"/de-DE/bundle/uniface_104/page/tlk1665702777147.html\"><svg aria-hidden=\"true\" class=\"ico-prev\"><use xlink:href=\"#ico-prev\"></use></svg></a></span></div><div class=\"zDocsNextTopicButton zDocsNextTopicButton\"><span class=\"\"><a aria-label=\"Next:  Data Packing for Microsoft SQL Server   \" class=\"\" data-tooltip-content=\"Next:  Data Packing for Microsoft SQL Server   \" data-tooltip-id=\"zDocsTopicActionsTooltip\" data-tooltip-open=\"false\" href=\"/de-DE/bundle/uniface_104/page/foe1665702727322.html\"><svg aria-hidden=\"true\" class=\"ico-next\"><use xlink:href=\"#ico-next\"></use></svg></a></span></div></div><div class=\"zDocsMyDocsMenu\" role=\"listitem\"><span aria-expanded=\"false\" aria-label=\"Add to My Topics\" class=\"d-none d-lg-flex\" data-toggle=\"dropdown\" data-tooltip-content=\"Add to My Topics\" data-tooltip-id=\"zDocsTopicActionsTooltip\" id=\"addToMyDocsDropdownTrigger\" role=\"button\" tabindex=\"0\"><svg aria-hidden=\"true\" class=\"ico-bookmark-add\"><use xlink:href=\"#ico-bookmark-add\"></use></svg></span><span class=\"d-lg-none d-flex\" role=\"button\" tabindex=\"0\"><svg aria-hidden=\"true\" class=\"ico-bookmark-add\"><use xlink:href=\"#ico-bookmark-add\"></use></svg>Add to My Topics</span><div aria-labelledby=\"pdfDropdown\" class=\"dropdown-menu dropdown-menu-right\"><a class=\"zDocsAddTopicButton zDocsMyDocsMenuItem dropdown-item\" href=\"/de-DE/auth/login?redirect=/bundle/uniface_104/page/brk1665702777359.html?finish_action=mydocs_topic_and_sub\">Add selected topic and subtopics</a><a class=\"zDocsAddTopicButton zDocsMyDocsMenuItem dropdown-item\" href=\"/de-DE/auth/login?redirect=/bundle/uniface_104/page/brk1665702777359.html?finish_action=mydocs_topic_and_sub_head\">Add Topic &amp; Subtopics with topic head</a><a class=\"zDocsAddTopicButton zDocsMyDocsMenuItem dropdown-item\" href=\"/de-DE/auth/login?redirect=/bundle/uniface_104/page/brk1665702777359.html?finish_action=mydocs_pub\">Add entire publication</a></div></div><div class=\"zDocsWatchButton\" role=\"listitem\"><span aria-label=\"Watch\" class=\"d-lg-flex d-none zDocsSubscribeButton\" data-tooltip-content=\"Watch\" data-tooltip-id=\"zDocsTopicActionsTooltip\" role=\"button\" tabindex=\"0\"><svg aria-hidden=\"true\" class=\"ico-eye\"><use xlink:href=\"#ico-eye\"></use></svg></span><span class=\"d-lg-none d-flex zDocsSubscribeButton\" role=\"button\" tabindex=\"0\"><svg aria-hidden=\"true\" class=\"ico-eye zDocsSubscribeButton\"><use xlink:href=\"#ico-eye\"></use></svg><span class=\"zDocsSubscribeButton\">Watch</span></span></div><div class=\"zDocsExportPdfMenu zDocsExportMenu\" data-testid=\"export-pdf-menu\" role=\"listitem\"><span aria-expanded=\"false\" aria-label=\"Download PDF\" class=\"d-none d-lg-flex\" data-toggle=\"dropdown\" data-tooltip-content=\"Download PDF\" data-tooltip-id=\"zDocsTopicActionsTooltip\" role=\"button\" tabindex=\"0\"><svg aria-hidden=\"true\" class=\"ico-pdf\"><use xlink:href=\"#ico-pdf\"></use></svg></span><span class=\"d-lg-none d-flex\" data-return-focus=\"#zDocsTopicActionsMobile\" data-target=\"#ZdExportPDFModal\" data-toggle=\"modal\" role=\"button\" tabindex=\"0\"><svg aria-hidden=\"true\" class=\"ico-pdf\"><use xlink:href=\"#ico-pdf\"></use></svg>Download PDF</span><div class=\"dropdown-menu zDocsDropdownMenu\"><a class=\"zDocsExportItem zDocsExportTopicButton\" href=\"#\" id=\"singlePdf\" role=\"button\">Save selected topic</a><a class=\"zDocsExportItem zDocsExportSubtopicsButton\" href=\"#\" id=\"pdfWithChildren\" role=\"button\">Save selected topic and subtopics</a><a class=\"zDocsExportItem zDocsExportBundleButton\" href=\"#\" id=\"wholeBundlePdf\" role=\"button\">Save entire publication</a></div></div><div class=\"zDocsTopicShare zDocsShareButton\" role=\"listitem\"><span aria-expanded=\"false\" aria-label=\"Share\" class=\"d-none d-lg-flex zDocsShareDialogButton\" data-toggle=\"dropdown\" data-tooltip-content=\"Share\" data-tooltip-id=\"zDocsTopicActionsTooltip\" role=\"button\" tabindex=\"0\"><svg aria-hidden=\"true\" class=\"ico-share\"><use xlink:href=\"#ico-share\"></use></svg></span><span class=\"d-lg-none zDocsShareDialogButton\" role=\"button\" tabindex=\"0\"><svg aria-hidden=\"true\" class=\"ico-share\"><use xlink:href=\"#ico-share\"></use></svg>Share</span><div class=\"dropdown-menu zDocsDropdownMenu\"><a class=\"dropdown-item zDocsShareButton zDocsShareEmail\" href=\"#\" role=\"button\"><span>Email Link</span></a><a class=\"dropdown-item zDocsShareButton zDocsShareLink\" href=\"#\" role=\"button\"><span>Copy Link</span></a></div></div><div class=\"zDocsFeedback zDocsFeedback zDocsTopicFeedback\" role=\"listitem\"><span aria-label=\"Feedback\" class=\"zDocsFeedbackButton d-none d-lg-flex\" data-backdrop=\"static\" data-target=\"#feedbackModal_main_2526197\" data-toggle=\"modal\" data-tooltip-content=\"Feedback\" data-tooltip-id=\"zDocsTopicActionsTooltip\" role=\"button\" tabindex=\"0\"><svg aria-hidden=\"true\" class=\"ico-feedback\"><use xlink:href=\"#ico-feedback\"></use></svg></span><span class=\"d-lg-none d-flex zDocsFeedbackButton\" data-backdrop=\"static\" data-return-focus=\"#zDocsTopicActionsMobile\" data-target=\"#feedbackModal_main_2526197\" data-toggle=\"modal\" role=\"button\" tabindex=\"0\"><svg aria-hidden=\"true\" class=\"ico-feedback\"><use xlink:href=\"#ico-feedback\"></use></svg><span class=\"zDocsFeedbackButtonText\"> Feedback</span></span></div></div><div class=\"zDocsTopicActionsMobile\"><button aria-label=\"Show topic actions\" data-toggle=\"dropdown\" id=\"zDocsTopicActionsMobile\"><svg aria-hidden=\"true\" class=\"ico-ellipsis-h\"><use xlink:href=\"#ico-ellipsis-h\"></use></svg></button><div class=\"dropdown-menu zDocsDropdownMenu zDocsTopicActionsMobileDropdown dropdown-menu-right\"></div></div><div style=\"flex-basis: 100%; height: 0px;\"></div><ul class=\"zDocsTopicPageDetails\"><li class=\"zDocsTopicPageDate css-cinqea\">Last Updated<span class=\"css-cinqea\">Aug 13, 2024</span></li><li class=\"zDocsAiTopicSummaryDetailsItem\"><button class=\"zDocsAiTopicSummaryButton\"><svg aria-hidden=\"true\" class=\"ico-topic-summary\"><use xlink:href=\"#ico-topic-summary\"></use></svg>Summarize</button></li><li class=\"spacer\" role=\"presentation\"></li><div class=\"zDocsLabelWrapper\"><ul><li class=\"zDocsLabel\"><a aria-describedby=\"hyperLinkFacetsTooltip\" class=\"css-ettsdk\" data-tooltip-content=\"Search all site by tag: Uniface\" data-tooltip-id=\"hyperLinkFacetsTooltip\" href=\"/de-DE/search?labelkey=prod_uniface\" stylesprops=\"[object Object]\"><svg aria-label=\"Tag\" class=\"ico-tag\" role=\"img\"><use xlink:href=\"#ico-tag\"></use></svg>Uniface</a></li><li class=\"zDocsLabel\"><a aria-describedby=\"hyperLinkFacetsTooltip\" class=\"css-ettsdk\" data-tooltip-content=\"Search all site by tag: 10.4\" data-tooltip-id=\"hyperLinkFacetsTooltip\" href=\"/de-DE/search?labelkey=uniface_10.4\" stylesprops=\"[object Object]\"><svg aria-label=\"Tag\" class=\"ico-tag\" role=\"img\"><use xlink:href=\"#ico-tag\"></use></svg>10.4</a></li></ul></div></ul></header><div class=\"zDocsTopicPageBody\" data-prismjs-copy=\"Copy\" data-prismjs-copy-error=\"Copy failed! Use Ctrl + C instead.\" data-prismjs-copy-success=\"Copied!\"><div class=\"zDocsTopicPageBodyContent\" dir=\"ltr\"><div id=\"zDocsAiSummaryContaineruniface_104brk1665702777359.html\"></div><div><article class=\"hascomments\" data-page=\"bundle:uniface_104/enus/brk1665702777359.html\" id=\"bundle:uniface_104/enus/brk1665702777359.html\"><main role=\"main\"><article aria-labelledby=\"ariaid-title1\" class=\"dita\" id=\"brk1665702777359\" role=\"article\">\n<h1 class=\"title topictitle1\" id=\"ariaid-title1\">\n      Service Stored Procedures on Microsoft SQL Server\n </h1>\n<div class=\"body conbody\"><p class=\"shortdesc\">Service stored procedures are supported for the Microsoft SQL Server connector.\n </p>\n<p class=\"p\" id=\"brk1665702777359__p_d53258e1_d53259e1_d53260e1\">The stored procedure name used for execution by Uniface is depends on the whether literal names have been defined in the signature of the Stored Procedure Component.</p>\n<div class=\"table-wrap\"><table class=\"table\" count-columns=\"4\" id=\"brk1665702777359__table_d4931e1_d4932e1_d4933e1\"><caption><span class=\"table--title-label\">Table 1. </span><span class=\"title\">Component Name and Operation Name Specification</span></caption><colgroup><col/><col/><col/><col/></colgroup><thead class=\"thead\">\n<tr class=\"row\" dir=\"ltr\">\n<th class=\"entry\" dir=\"ltr\" id=\"brk1665702777359__table_d4931e1_d4932e1_d4933e1__entry__1\">\n<p class=\"p\">Literal Component Name</p>\n</th>\n<th class=\"entry\" dir=\"ltr\" id=\"brk1665702777359__table_d4931e1_d4932e1_d4933e1__entry__2\">\n<p class=\"p\">Literal Operation Name</p>\n</th>\n<th class=\"entry\" dir=\"ltr\" id=\"brk1665702777359__table_d4931e1_d4932e1_d4933e1__entry__3\">\n<p class=\"p\">Stored Procedure Name</p>\n</th>\n<th class=\"entry\" dir=\"ltr\" id=\"brk1665702777359__table_d4931e1_d4932e1_d4933e1__entry__4\">\n<p class=\"p\">Example</p>\n</th>\n</tr>\n</thead><tbody class=\"tbody\">\n<tr class=\"row\" dir=\"ltr\">\n<td class=\"entry\" dir=\"ltr\" headers=\"brk1665702777359__table_d4931e1_d4932e1_d4933e1__entry__1\">\n<p class=\"p\">—</p>\n</td>\n<td class=\"entry\" dir=\"ltr\" headers=\"brk1665702777359__table_d4931e1_d4932e1_d4933e1__entry__2\">\n<p class=\"p\">—</p>\n</td>\n<td class=\"entry\" dir=\"ltr\" headers=\"brk1665702777359__table_d4931e1_d4932e1_d4933e1__entry__3\">\n<p class=\"p\">\n<var class=\"keyword varname\">UnifaceComponentName.UnifaceOperationName</var>\n</p>\n</td>\n<td class=\"entry\" dir=\"ltr\" headers=\"brk1665702777359__table_d4931e1_d4932e1_d4933e1__entry__4\">\n<p class=\"p\">\n<code class=\"ph codeph\">MY_CPT.SP1</code>\n</p>\n</td>\n</tr>\n<tr class=\"row\" dir=\"ltr\">\n<td class=\"entry\" dir=\"ltr\" headers=\"brk1665702777359__table_d4931e1_d4932e1_d4933e1__entry__1\" rowspan=\"3\">\n<p class=\"p\">—</p>\n</td>\n<td class=\"entry\" dir=\"ltr\" headers=\"brk1665702777359__table_d4931e1_d4932e1_d4933e1__entry__2\" rowspan=\"3\">\n<p class=\"p\">Specified</p>\n</td>\n<td class=\"entry\" dir=\"ltr\" headers=\"brk1665702777359__table_d4931e1_d4932e1_d4933e1__entry__3\">\n<p class=\"p\">\n<var class=\"keyword varname\">LiteralOperationName</var>\n                        1\n                     </p>\n</td>\n<td class=\"entry\" dir=\"ltr\" headers=\"brk1665702777359__table_d4931e1_d4932e1_d4933e1__entry__4\">\n<p class=\"p\">\n<code class=\"ph codeph\">sp1</code>\n</p>\n</td>\n</tr>\n<tr class=\"row\" dir=\"ltr\">\n<td class=\"entry\" dir=\"ltr\" headers=\"brk1665702777359__table_d4931e1_d4932e1_d4933e1__entry__3\">\n<p class=\"p\">\n<var class=\"keyword varname\">SchemaName.OperationName</var>\n                        2\n                     </p>\n</td>\n<td class=\"entry\" dir=\"ltr\" headers=\"brk1665702777359__table_d4931e1_d4932e1_d4933e1__entry__4\">\n<p class=\"p\">\n<code class=\"ph codeph\">schema.sp1</code>\n</p>\n</td>\n</tr>\n<tr class=\"row\" dir=\"ltr\">\n<td class=\"entry\" dir=\"ltr\" headers=\"brk1665702777359__table_d4931e1_d4932e1_d4933e1__entry__3\">\n<p class=\"p\">\n<var class=\"keyword varname\">DbOwner.LiteralOperationName</var>\n                        3\n                     </p>\n</td>\n<td class=\"entry\" dir=\"ltr\" headers=\"brk1665702777359__table_d4931e1_d4932e1_d4933e1__entry__4\">\n<p class=\"p\">\n<code class=\"ph codeph\">dbo.sp1</code>\n</p>\n</td>\n</tr>\n<tr class=\"row\" dir=\"ltr\">\n<td class=\"entry\" dir=\"ltr\" headers=\"brk1665702777359__table_d4931e1_d4932e1_d4933e1__entry__1\">\n<p class=\"p\">Specified</p>\n</td>\n<td class=\"entry\" dir=\"ltr\" headers=\"brk1665702777359__table_d4931e1_d4932e1_d4933e1__entry__2\">\n<p class=\"p\">—</p>\n</td>\n<td class=\"entry\" dir=\"ltr\" headers=\"brk1665702777359__table_d4931e1_d4932e1_d4933e1__entry__3\">\n<p class=\"p\">\n<var class=\"keyword varname\">LiteralComponentName.UnifaceOperationName</var>\n</p>\n</td>\n<td class=\"entry\" dir=\"ltr\" headers=\"brk1665702777359__table_d4931e1_d4932e1_d4933e1__entry__4\">\n<p class=\"p\">\n<code class=\"ph codeph\">sp.SP1</code>\n</p>\n</td>\n</tr>\n<tr class=\"row\" dir=\"ltr\">\n<td class=\"entry\" dir=\"ltr\" headers=\"brk1665702777359__table_d4931e1_d4932e1_d4933e1__entry__1\" rowspan=\"2\">\n<p class=\"p\">Specified</p>\n</td>\n<td class=\"entry\" dir=\"ltr\" headers=\"brk1665702777359__table_d4931e1_d4932e1_d4933e1__entry__2\" rowspan=\"2\">\n<p class=\"p\">Specified</p>\n</td>\n<td class=\"entry\" dir=\"ltr\" headers=\"brk1665702777359__table_d4931e1_d4932e1_d4933e1__entry__3\">\n<p class=\"p\">\n<var class=\"keyword varname\">LiteralComponentName.LiteralOperationName</var>\n</p>\n</td>\n<td class=\"entry\" dir=\"ltr\" headers=\"brk1665702777359__table_d4931e1_d4932e1_d4933e1__entry__4\">\n<p class=\"p\">\n<code class=\"ph codeph\">sp.sp1</code>\n</p>\n</td>\n</tr>\n<tr class=\"row\" dir=\"ltr\">\n<td class=\"entry\" dir=\"ltr\" headers=\"brk1665702777359__table_d4931e1_d4932e1_d4933e1__entry__3\">\n<p class=\"p\">\n<var class=\"keyword varname\">SchemaName.OperationName</var>\n                        2\n                     </p>\n</td>\n<td class=\"entry\" dir=\"ltr\" headers=\"brk1665702777359__table_d4931e1_d4932e1_d4933e1__entry__4\">\n<p class=\"p\">\n<code class=\"ph codeph\">schema.sp1</code>\n</p>\n</td>\n</tr>\n<tr class=\"row\" dir=\"ltr\">\n<td class=\"entry\" colspan=\"4\" dir=\"ltr\" headers=\"brk1665702777359__table_d4931e1_d4932e1_d4933e1__entry__1 brk1665702777359__table_d4931e1_d4932e1_d4933e1__entry__2 brk1665702777359__table_d4931e1_d4932e1_d4933e1__entry__3 brk1665702777359__table_d4931e1_d4932e1_d4933e1__entry__4\">\n<ul class=\"ul\">\n<li class=\"li\" id=\"brk1665702777359__li_d24938e1_d24939e1_d24940e1\">\n<var class=\"keyword varname\">UnifaceComponentName</var>: <code class=\"ph codeph\">MY_CPT</code>\n</li>\n<li class=\"li\" id=\"brk1665702777359__li_d24941e1_d24942e1_d24943e1\">\n<var class=\"keyword varname\">UnifaceOperationName</var>: <code class=\"ph codeph\">SP1</code>\n</li>\n</ul>\n<ol class=\"ol\">\n<li class=\"li\" id=\"brk1665702777359__li_d24944e1_d24945e1_d24946e1\">If <var class=\"keyword varname\">LiteralOperationName</var> does not include a schema name, the default schema of the user is used.\n </li>\n<li class=\"li\" id=\"brk1665702777359__li_d24947e1_d24948e1_d24949e1\">If <var class=\"keyword varname\">LiteralOperationName</var> includes a schema name (for example, <var class=\"keyword varname\">SchemaName.OperationName</var>), the stored procedure will be called as <var class=\"keyword varname\">SchemaName.OperationName</var>. If a literal component name is also specified, it is ignored.\n <div class=\"note caution note_caution\" id=\"brk1665702777359__note_w3445ab1b5b3b3c11c15b1b3b3b7_w3446ab1b5b3b3c11c15b1b3b3_w3447ab1b5b3b3c11c15b1b3_w3448ab1b5b3b3c11c15b1_w3449ab1b5b3b3c11c15_w3450ab1b5b3b3c11_w3451ab1b5b3b3_w3452ab1b5b3_w3453ab1b5_w3454ab1\"><span class=\"note__title\">CAUTION:</span> This is not recommended because it will not run on other databases connectors.</div>\n</li>\n<li class=\"li\" id=\"brk1665702777359__li_d24950e1_d24951e1_d24952e1\">If the <span class=\"keyword cmdname\">dbowner</span> option is specified, it is prefixed to the operation name and used instead of the default schema of the user.\n </li>\n</ol>\n</td>\n</tr>\n</tbody></table></div>\n<p class=\"p\" id=\"brk1665702777359__p_d53261e1_d53262e1_d53263e1\">Parameter names are not used during the execution of stored procedures. However, their order (that is, their relative position) is used for mapping parameters. For more information, see <a class=\"xref\" data-bundleid=\"uniface_104\" data-navpath=\"yqa1665702772542.html\" href=\"/de-DE/bundle/uniface_104/page/yqa1665702772542.html\" title=\"For Service Stored Procedures, the signature of the Stored Procedure Component maps the names of Uniface components, operations, and parameters to the name of a package, procedure, and parameter names in the procedure.\">Naming Specifications for Service Store Procedures</a>.</p>\n<section class=\"section\" id=\"brk1665702777359__section_epq_bxl_jcc\"><h2 class=\"title sectiontitle\" id=\"d365194e368\">Database Case Sensitivity</h2>\n<p class=\"p\" id=\"brk1665702777359__p_d53267e1_d53268e1_d53269e1\">If the SQL database is defined as case-sensitive and\n            your schema name and procedure name are not all in uppercase, you can use literal\n            component name and literal operation name to resolve the issue.</p>\n<p class=\"p\" id=\"brk1665702777359__p_d53270e1_d53271e1_d53272e1\">For example, a database is defined as case-sensitive,\n            the database schema is named <code class=\"ph codeph\">MySchema</code>, and the stored procedure is\n            named <code class=\"ph codeph\">myproc1</code>. When defining the operation name in the Uniface\n            signature component, you can do one of the following:</p>\n<ul class=\"ul\" id=\"brk1665702777359__ul_prn_dxl_jcc\">\n<li class=\"li\" id=\"brk1665702777359__li_d24953e1_d24954e1_d24955e1\">Define the component literal name as:\n                  <code class=\"ph codeph\">MySchema1</code>, and define operation literal name as\n                  <code class=\"ph codeph\">myproc1</code>. </li>\n<li class=\"li\" id=\"brk1665702777359__li_d24956e1_d24957e1_d24958e1\">Put all stored procedures in a shared schema and\n               use the <span class=\"keyword cmdname\">dbowner</span> option to specify this schema. For more\n               information, see <a class=\"xref\" data-bundleid=\"uniface_104\" data-navpath=\"aci1665702729371.html\" href=\"/de-DE/bundle/uniface_104/page/aci1665702729371.html\" title=\"Specify that called stored procedures should be prefixed with the owner name.\">dbowner</a>. </li>\n</ul>\n</section>\n<section class=\"section\" id=\"brk1665702777359__section_rv1_2xl_jcc\"><h2 class=\"title sectiontitle\" id=\"d365194e411\">Entity Parameters</h2>\n<p class=\"p\" id=\"brk1665702777359__p_d53276e1_d53277e1_d53278e1\">When defining an operation with an entity parameter in\n            a Uniface signature, you can define an entity parameter only as OUT or INOUT, but when\n            creating the corresponding stored procedure in SQL Server, you must define the parameter\n            as an OUTPUT string. Also, the name of the Uniface entity parameter must be identical to\n            the name of the table in the database. See the example below.</p>\n</section>\n<section class=\"section\" id=\"brk1665702777359__section_ygr_gxl_jcc\"><h2 class=\"title sectiontitle\" id=\"d365194e421\">Data Conversions</h2>\n<p class=\"p\" id=\"brk1665702777359__p_d53282e1_d53283e1_d53284e1\">The data types of operation parameters must closely\n            match the stored procedure parameters. If necessary, explicit and implicit conversions\n            are used to achieve an optimal mapping for all data types.</p>\n<p class=\"p\" id=\"brk1665702777359__p_d53285e1_d53286e1_d53287e1\">The supported parameter data type mappings for the MS\n            SQL Server are shown in the following table. (The data type mappings shown in the table\n            apply to both basic parameters and entity parameters.)</p>\n<div class=\"table-wrap\"><table class=\"table\" count-columns=\"8\" id=\"brk1665702777359__table_d4934e1_d4935e1_d4936e1\"><caption><span class=\"table--title-label\">Table 2. </span><span class=\"title\">Uniface to Microsoft SQL Server Parameter–Data Type Mappings</span></caption><colgroup><col/><col/><col/><col/><col/><col/><col/><col/></colgroup><thead class=\"thead\">\n<tr class=\"row\" dir=\"ltr\">\n<th class=\"entry\" dir=\"ltr\" id=\"brk1665702777359__table_d4934e1_d4935e1_d4936e1__entry__1\"></th>\n<th class=\"entry\" colspan=\"7\" dir=\"ltr\" id=\"brk1665702777359__table_d4934e1_d4935e1_d4936e1__entry__2\">Uniface Parameter Data Types\n                     </th>\n</tr>\n<tr class=\"row\" dir=\"ltr\">\n<th class=\"entry\" dir=\"ltr\" id=\"brk1665702777359__table_d4934e1_d4935e1_d4936e1__entry__3\">MS SQL Data Types </th>\n<th class=\"entry\" dir=\"ltr\" id=\"brk1665702777359__table_d4934e1_d4935e1_d4936e1__entry__4\">String </th>\n<th class=\"entry\" dir=\"ltr\" id=\"brk1665702777359__table_d4934e1_d4935e1_d4936e1__entry__5\">Boolean </th>\n<th class=\"entry\" dir=\"ltr\" id=\"brk1665702777359__table_d4934e1_d4935e1_d4936e1__entry__6\">Numeric </th>\n<th class=\"entry\" dir=\"ltr\" id=\"brk1665702777359__table_d4934e1_d4935e1_d4936e1__entry__7\">Float </th>\n<th class=\"entry\" dir=\"ltr\" id=\"brk1665702777359__table_d4934e1_d4935e1_d4936e1__entry__8\">(L)Date </th>\n<th class=\"entry\" dir=\"ltr\" id=\"brk1665702777359__table_d4934e1_d4935e1_d4936e1__entry__9\">(L)Time </th>\n<th class=\"entry\" dir=\"ltr\" id=\"brk1665702777359__table_d4934e1_d4935e1_d4936e1__entry__10\">(L)Datetime </th>\n</tr>\n</thead><tbody class=\"tbody\">\n<tr class=\"row\" dir=\"ltr\">\n<td class=\"entry\" dir=\"ltr\" headers=\"brk1665702777359__table_d4934e1_d4935e1_d4936e1__entry__1 brk1665702777359__table_d4934e1_d4935e1_d4936e1__entry__3\">char </td>\n<td class=\"entry\" dir=\"ltr\" headers=\"brk1665702777359__table_d4934e1_d4935e1_d4936e1__entry__2 brk1665702777359__table_d4934e1_d4935e1_d4936e1__entry__4\">Y </td>\n<td class=\"entry\" dir=\"ltr\" headers=\"brk1665702777359__table_d4934e1_d4935e1_d4936e1__entry__2 brk1665702777359__table_d4934e1_d4935e1_d4936e1__entry__5\">Y </td>\n<td class=\"entry\" dir=\"ltr\" headers=\"brk1665702777359__table_d4934e1_d4935e1_d4936e1__entry__2 brk1665702777359__table_d4934e1_d4935e1_d4936e1__entry__6\">Y </td>\n<td class=\"entry\" dir=\"ltr\" headers=\"brk1665702777359__table_d4934e1_d4935e1_d4936e1__entry__2 brk1665702777359__table_d4934e1_d4935e1_d4936e1__entry__7\">Y </td>\n<td class=\"entry\" dir=\"ltr\" headers=\"brk1665702777359__table_d4934e1_d4935e1_d4936e1__entry__2 brk1665702777359__table_d4934e1_d4935e1_d4936e1__entry__8\"></td>\n<td class=\"entry\" dir=\"ltr\" headers=\"brk1665702777359__table_d4934e1_d4935e1_d4936e1__entry__2 brk1665702777359__table_d4934e1_d4935e1_d4936e1__entry__9\"></td>\n<td class=\"entry\" dir=\"ltr\" headers=\"brk1665702777359__table_d4934e1_d4935e1_d4936e1__entry__2 brk1665702777359__table_d4934e1_d4935e1_d4936e1__entry__10\"></td>\n</tr>\n<tr class=\"row\" dir=\"ltr\">\n<td class=\"entry\" dir=\"ltr\" headers=\"brk1665702777359__table_d4934e1_d4935e1_d4936e1__entry__1 brk1665702777359__table_d4934e1_d4935e1_d4936e1__entry__3\">nchar </td>\n<td class=\"entry\" dir=\"ltr\" headers=\"brk1665702777359__table_d4934e1_d4935e1_d4936e1__entry__2 brk1665702777359__table_d4934e1_d4935e1_d4936e1__entry__4\">Y </td>\n<td class=\"entry\" dir=\"ltr\" headers=\"brk1665702777359__table_d4934e1_d4935e1_d4936e1__entry__2 brk1665702777359__table_d4934e1_d4935e1_d4936e1__entry__5\">Y </td>\n<td class=\"entry\" dir=\"ltr\" headers=\"brk1665702777359__table_d4934e1_d4935e1_d4936e1__entry__2 brk1665702777359__table_d4934e1_d4935e1_d4936e1__entry__6\">Y </td>\n<td class=\"entry\" dir=\"ltr\" headers=\"brk1665702777359__table_d4934e1_d4935e1_d4936e1__entry__2 brk1665702777359__table_d4934e1_d4935e1_d4936e1__entry__7\">Y </td>\n<td class=\"entry\" dir=\"ltr\" headers=\"brk1665702777359__table_d4934e1_d4935e1_d4936e1__entry__2 brk1665702777359__table_d4934e1_d4935e1_d4936e1__entry__8\"></td>\n<td class=\"entry\" dir=\"ltr\" headers=\"brk1665702777359__table_d4934e1_d4935e1_d4936e1__entry__2 brk1665702777359__table_d4934e1_d4935e1_d4936e1__entry__9\"></td>\n<td class=\"entry\" dir=\"ltr\" headers=\"brk1665702777359__table_d4934e1_d4935e1_d4936e1__entry__2 brk1665702777359__table_d4934e1_d4935e1_d4936e1__entry__10\"></td>\n</tr>\n<tr class=\"row\" dir=\"ltr\">\n<td class=\"entry\" dir=\"ltr\" headers=\"brk1665702777359__table_d4934e1_d4935e1_d4936e1__entry__1 brk1665702777359__table_d4934e1_d4935e1_d4936e1__entry__3\">varchar </td>\n<td class=\"entry\" dir=\"ltr\" headers=\"brk1665702777359__table_d4934e1_d4935e1_d4936e1__entry__2 brk1665702777359__table_d4934e1_d4935e1_d4936e1__entry__4\">Y </td>\n<td class=\"entry\" dir=\"ltr\" headers=\"brk1665702777359__table_d4934e1_d4935e1_d4936e1__entry__2 brk1665702777359__table_d4934e1_d4935e1_d4936e1__entry__5\">Y </td>\n<td class=\"entry\" dir=\"ltr\" headers=\"brk1665702777359__table_d4934e1_d4935e1_d4936e1__entry__2 brk1665702777359__table_d4934e1_d4935e1_d4936e1__entry__6\">Y </td>\n<td class=\"entry\" dir=\"ltr\" headers=\"brk1665702777359__table_d4934e1_d4935e1_d4936e1__entry__2 brk1665702777359__table_d4934e1_d4935e1_d4936e1__entry__7\">Y </td>\n<td class=\"entry\" dir=\"ltr\" headers=\"brk1665702777359__table_d4934e1_d4935e1_d4936e1__entry__2 brk1665702777359__table_d4934e1_d4935e1_d4936e1__entry__8\"></td>\n<td class=\"entry\" dir=\"ltr\" headers=\"brk1665702777359__table_d4934e1_d4935e1_d4936e1__entry__2 brk1665702777359__table_d4934e1_d4935e1_d4936e1__entry__9\"></td>\n<td class=\"entry\" dir=\"ltr\" headers=\"brk1665702777359__table_d4934e1_d4935e1_d4936e1__entry__2 brk1665702777359__table_d4934e1_d4935e1_d4936e1__entry__10\"></td>\n</tr>\n<tr class=\"row\" dir=\"ltr\">\n<td class=\"entry\" dir=\"ltr\" headers=\"brk1665702777359__table_d4934e1_d4935e1_d4936e1__entry__1 brk1665702777359__table_d4934e1_d4935e1_d4936e1__entry__3\">nvarchar </td>\n<td class=\"entry\" dir=\"ltr\" headers=\"brk1665702777359__table_d4934e1_d4935e1_d4936e1__entry__2 brk1665702777359__table_d4934e1_d4935e1_d4936e1__entry__4\">Y </td>\n<td class=\"entry\" dir=\"ltr\" headers=\"brk1665702777359__table_d4934e1_d4935e1_d4936e1__entry__2 brk1665702777359__table_d4934e1_d4935e1_d4936e1__entry__5\">Y </td>\n<td class=\"entry\" dir=\"ltr\" headers=\"brk1665702777359__table_d4934e1_d4935e1_d4936e1__entry__2 brk1665702777359__table_d4934e1_d4935e1_d4936e1__entry__6\">Y </td>\n<td class=\"entry\" dir=\"ltr\" headers=\"brk1665702777359__table_d4934e1_d4935e1_d4936e1__entry__2 brk1665702777359__table_d4934e1_d4935e1_d4936e1__entry__7\">Y </td>\n<td class=\"entry\" dir=\"ltr\" headers=\"brk1665702777359__table_d4934e1_d4935e1_d4936e1__entry__2 brk1665702777359__table_d4934e1_d4935e1_d4936e1__entry__8\"></td>\n<td class=\"entry\" dir=\"ltr\" headers=\"brk1665702777359__table_d4934e1_d4935e1_d4936e1__entry__2 brk1665702777359__table_d4934e1_d4935e1_d4936e1__entry__9\"></td>\n<td class=\"entry\" dir=\"ltr\" headers=\"brk1665702777359__table_d4934e1_d4935e1_d4936e1__entry__2 brk1665702777359__table_d4934e1_d4935e1_d4936e1__entry__10\"></td>\n</tr>\n<tr class=\"row\" dir=\"ltr\">\n<td class=\"entry\" dir=\"ltr\" headers=\"brk1665702777359__table_d4934e1_d4935e1_d4936e1__entry__1 brk1665702777359__table_d4934e1_d4935e1_d4936e1__entry__3\">decimal </td>\n<td class=\"entry\" dir=\"ltr\" headers=\"brk1665702777359__table_d4934e1_d4935e1_d4936e1__entry__2 brk1665702777359__table_d4934e1_d4935e1_d4936e1__entry__4\">Y </td>\n<td class=\"entry\" dir=\"ltr\" headers=\"brk1665702777359__table_d4934e1_d4935e1_d4936e1__entry__2 brk1665702777359__table_d4934e1_d4935e1_d4936e1__entry__5\">Y </td>\n<td class=\"entry\" dir=\"ltr\" headers=\"brk1665702777359__table_d4934e1_d4935e1_d4936e1__entry__2 brk1665702777359__table_d4934e1_d4935e1_d4936e1__entry__6\">Y </td>\n<td class=\"entry\" dir=\"ltr\" headers=\"brk1665702777359__table_d4934e1_d4935e1_d4936e1__entry__2 brk1665702777359__table_d4934e1_d4935e1_d4936e1__entry__7\">Y </td>\n<td class=\"entry\" dir=\"ltr\" headers=\"brk1665702777359__table_d4934e1_d4935e1_d4936e1__entry__2 brk1665702777359__table_d4934e1_d4935e1_d4936e1__entry__8\"></td>\n<td class=\"entry\" dir=\"ltr\" headers=\"brk1665702777359__table_d4934e1_d4935e1_d4936e1__entry__2 brk1665702777359__table_d4934e1_d4935e1_d4936e1__entry__9\"></td>\n<td class=\"entry\" dir=\"ltr\" headers=\"brk1665702777359__table_d4934e1_d4935e1_d4936e1__entry__2 brk1665702777359__table_d4934e1_d4935e1_d4936e1__entry__10\"></td>\n</tr>\n<tr class=\"row\" dir=\"ltr\">\n<td class=\"entry\" dir=\"ltr\" headers=\"brk1665702777359__table_d4934e1_d4935e1_d4936e1__entry__1 brk1665702777359__table_d4934e1_d4935e1_d4936e1__entry__3\">numeric </td>\n<td class=\"entry\" dir=\"ltr\" headers=\"brk1665702777359__table_d4934e1_d4935e1_d4936e1__entry__2 brk1665702777359__table_d4934e1_d4935e1_d4936e1__entry__4\">Y </td>\n<td class=\"entry\" dir=\"ltr\" headers=\"brk1665702777359__table_d4934e1_d4935e1_d4936e1__entry__2 brk1665702777359__table_d4934e1_d4935e1_d4936e1__entry__5\">Y </td>\n<td class=\"entry\" dir=\"ltr\" headers=\"brk1665702777359__table_d4934e1_d4935e1_d4936e1__entry__2 brk1665702777359__table_d4934e1_d4935e1_d4936e1__entry__6\">Y </td>\n<td class=\"entry\" dir=\"ltr\" headers=\"brk1665702777359__table_d4934e1_d4935e1_d4936e1__entry__2 brk1665702777359__table_d4934e1_d4935e1_d4936e1__entry__7\">Y </td>\n<td class=\"entry\" dir=\"ltr\" headers=\"brk1665702777359__table_d4934e1_d4935e1_d4936e1__entry__2 brk1665702777359__table_d4934e1_d4935e1_d4936e1__entry__8\"></td>\n<td class=\"entry\" dir=\"ltr\" headers=\"brk1665702777359__table_d4934e1_d4935e1_d4936e1__entry__2 brk1665702777359__table_d4934e1_d4935e1_d4936e1__entry__9\"></td>\n<td class=\"entry\" dir=\"ltr\" headers=\"brk1665702777359__table_d4934e1_d4935e1_d4936e1__entry__2 brk1665702777359__table_d4934e1_d4935e1_d4936e1__entry__10\"></td>\n</tr>\n<tr class=\"row\" dir=\"ltr\">\n<td class=\"entry\" dir=\"ltr\" headers=\"brk1665702777359__table_d4934e1_d4935e1_d4936e1__entry__1 brk1665702777359__table_d4934e1_d4935e1_d4936e1__entry__3\">tinyint </td>\n<td class=\"entry\" dir=\"ltr\" headers=\"brk1665702777359__table_d4934e1_d4935e1_d4936e1__entry__2 brk1665702777359__table_d4934e1_d4935e1_d4936e1__entry__4\">Y </td>\n<td class=\"entry\" dir=\"ltr\" headers=\"brk1665702777359__table_d4934e1_d4935e1_d4936e1__entry__2 brk1665702777359__table_d4934e1_d4935e1_d4936e1__entry__5\">Y </td>\n<td class=\"entry\" dir=\"ltr\" headers=\"brk1665702777359__table_d4934e1_d4935e1_d4936e1__entry__2 brk1665702777359__table_d4934e1_d4935e1_d4936e1__entry__6\">Y </td>\n<td class=\"entry\" dir=\"ltr\" headers=\"brk1665702777359__table_d4934e1_d4935e1_d4936e1__entry__2 brk1665702777359__table_d4934e1_d4935e1_d4936e1__entry__7\">Y </td>\n<td class=\"entry\" dir=\"ltr\" headers=\"brk1665702777359__table_d4934e1_d4935e1_d4936e1__entry__2 brk1665702777359__table_d4934e1_d4935e1_d4936e1__entry__8\"></td>\n<td class=\"entry\" dir=\"ltr\" headers=\"brk1665702777359__table_d4934e1_d4935e1_d4936e1__entry__2 brk1665702777359__table_d4934e1_d4935e1_d4936e1__entry__9\"></td>\n<td class=\"entry\" dir=\"ltr\" headers=\"brk1665702777359__table_d4934e1_d4935e1_d4936e1__entry__2 brk1665702777359__table_d4934e1_d4935e1_d4936e1__entry__10\"></td>\n</tr>\n<tr class=\"row\" dir=\"ltr\">\n<td class=\"entry\" dir=\"ltr\" headers=\"brk1665702777359__table_d4934e1_d4935e1_d4936e1__entry__1 brk1665702777359__table_d4934e1_d4935e1_d4936e1__entry__3\">smallint </td>\n<td class=\"entry\" dir=\"ltr\" headers=\"brk1665702777359__table_d4934e1_d4935e1_d4936e1__entry__2 brk1665702777359__table_d4934e1_d4935e1_d4936e1__entry__4\">Y </td>\n<td class=\"entry\" dir=\"ltr\" headers=\"brk1665702777359__table_d4934e1_d4935e1_d4936e1__entry__2 brk1665702777359__table_d4934e1_d4935e1_d4936e1__entry__5\">Y </td>\n<td class=\"entry\" dir=\"ltr\" headers=\"brk1665702777359__table_d4934e1_d4935e1_d4936e1__entry__2 brk1665702777359__table_d4934e1_d4935e1_d4936e1__entry__6\">Y </td>\n<td class=\"entry\" dir=\"ltr\" headers=\"brk1665702777359__table_d4934e1_d4935e1_d4936e1__entry__2 brk1665702777359__table_d4934e1_d4935e1_d4936e1__entry__7\">Y </td>\n<td class=\"entry\" dir=\"ltr\" headers=\"brk1665702777359__table_d4934e1_d4935e1_d4936e1__entry__2 brk1665702777359__table_d4934e1_d4935e1_d4936e1__entry__8\"></td>\n<td class=\"entry\" dir=\"ltr\" headers=\"brk1665702777359__table_d4934e1_d4935e1_d4936e1__entry__2 brk1665702777359__table_d4934e1_d4935e1_d4936e1__entry__9\"></td>\n<td class=\"entry\" dir=\"ltr\" headers=\"brk1665702777359__table_d4934e1_d4935e1_d4936e1__entry__2 brk1665702777359__table_d4934e1_d4935e1_d4936e1__entry__10\"></td>\n</tr>\n<tr class=\"row\" dir=\"ltr\">\n<td class=\"entry\" dir=\"ltr\" headers=\"brk1665702777359__table_d4934e1_d4935e1_d4936e1__entry__1 brk1665702777359__table_d4934e1_d4935e1_d4936e1__entry__3\">mediumint </td>\n<td class=\"entry\" dir=\"ltr\" headers=\"brk1665702777359__table_d4934e1_d4935e1_d4936e1__entry__2 brk1665702777359__table_d4934e1_d4935e1_d4936e1__entry__4\">Y </td>\n<td class=\"entry\" dir=\"ltr\" headers=\"brk1665702777359__table_d4934e1_d4935e1_d4936e1__entry__2 brk1665702777359__table_d4934e1_d4935e1_d4936e1__entry__5\">Y </td>\n<td class=\"entry\" dir=\"ltr\" headers=\"brk1665702777359__table_d4934e1_d4935e1_d4936e1__entry__2 brk1665702777359__table_d4934e1_d4935e1_d4936e1__entry__6\">Y </td>\n<td class=\"entry\" dir=\"ltr\" headers=\"brk1665702777359__table_d4934e1_d4935e1_d4936e1__entry__2 brk1665702777359__table_d4934e1_d4935e1_d4936e1__entry__7\">Y </td>\n<td class=\"entry\" dir=\"ltr\" headers=\"brk1665702777359__table_d4934e1_d4935e1_d4936e1__entry__2 brk1665702777359__table_d4934e1_d4935e1_d4936e1__entry__8\"></td>\n<td class=\"entry\" dir=\"ltr\" headers=\"brk1665702777359__table_d4934e1_d4935e1_d4936e1__entry__2 brk1665702777359__table_d4934e1_d4935e1_d4936e1__entry__9\"></td>\n<td class=\"entry\" dir=\"ltr\" headers=\"brk1665702777359__table_d4934e1_d4935e1_d4936e1__entry__2 brk1665702777359__table_d4934e1_d4935e1_d4936e1__entry__10\"></td>\n</tr>\n<tr class=\"row\" dir=\"ltr\">\n<td class=\"entry\" dir=\"ltr\" headers=\"brk1665702777359__table_d4934e1_d4935e1_d4936e1__entry__1 brk1665702777359__table_d4934e1_d4935e1_d4936e1__entry__3\">bigint </td>\n<td class=\"entry\" dir=\"ltr\" headers=\"brk1665702777359__table_d4934e1_d4935e1_d4936e1__entry__2 brk1665702777359__table_d4934e1_d4935e1_d4936e1__entry__4\">Y </td>\n<td class=\"entry\" dir=\"ltr\" headers=\"brk1665702777359__table_d4934e1_d4935e1_d4936e1__entry__2 brk1665702777359__table_d4934e1_d4935e1_d4936e1__entry__5\">Y </td>\n<td class=\"entry\" dir=\"ltr\" headers=\"brk1665702777359__table_d4934e1_d4935e1_d4936e1__entry__2 brk1665702777359__table_d4934e1_d4935e1_d4936e1__entry__6\">Y </td>\n<td class=\"entry\" dir=\"ltr\" headers=\"brk1665702777359__table_d4934e1_d4935e1_d4936e1__entry__2 brk1665702777359__table_d4934e1_d4935e1_d4936e1__entry__7\">Y </td>\n<td class=\"entry\" dir=\"ltr\" headers=\"brk1665702777359__table_d4934e1_d4935e1_d4936e1__entry__2 brk1665702777359__table_d4934e1_d4935e1_d4936e1__entry__8\"></td>\n<td class=\"entry\" dir=\"ltr\" headers=\"brk1665702777359__table_d4934e1_d4935e1_d4936e1__entry__2 brk1665702777359__table_d4934e1_d4935e1_d4936e1__entry__9\"></td>\n<td class=\"entry\" dir=\"ltr\" headers=\"brk1665702777359__table_d4934e1_d4935e1_d4936e1__entry__2 brk1665702777359__table_d4934e1_d4935e1_d4936e1__entry__10\"></td>\n</tr>\n<tr class=\"row\" dir=\"ltr\">\n<td class=\"entry\" dir=\"ltr\" headers=\"brk1665702777359__table_d4934e1_d4935e1_d4936e1__entry__1 brk1665702777359__table_d4934e1_d4935e1_d4936e1__entry__3\">int </td>\n<td class=\"entry\" dir=\"ltr\" headers=\"brk1665702777359__table_d4934e1_d4935e1_d4936e1__entry__2 brk1665702777359__table_d4934e1_d4935e1_d4936e1__entry__4\">Y </td>\n<td class=\"entry\" dir=\"ltr\" headers=\"brk1665702777359__table_d4934e1_d4935e1_d4936e1__entry__2 brk1665702777359__table_d4934e1_d4935e1_d4936e1__entry__5\">Y </td>\n<td class=\"entry\" dir=\"ltr\" headers=\"brk1665702777359__table_d4934e1_d4935e1_d4936e1__entry__2 brk1665702777359__table_d4934e1_d4935e1_d4936e1__entry__6\">Y </td>\n<td class=\"entry\" dir=\"ltr\" headers=\"brk1665702777359__table_d4934e1_d4935e1_d4936e1__entry__2 brk1665702777359__table_d4934e1_d4935e1_d4936e1__entry__7\">Y </td>\n<td class=\"entry\" dir=\"ltr\" headers=\"brk1665702777359__table_d4934e1_d4935e1_d4936e1__entry__2 brk1665702777359__table_d4934e1_d4935e1_d4936e1__entry__8\"></td>\n<td class=\"entry\" dir=\"ltr\" headers=\"brk1665702777359__table_d4934e1_d4935e1_d4936e1__entry__2 brk1665702777359__table_d4934e1_d4935e1_d4936e1__entry__9\"></td>\n<td class=\"entry\" dir=\"ltr\" headers=\"brk1665702777359__table_d4934e1_d4935e1_d4936e1__entry__2 brk1665702777359__table_d4934e1_d4935e1_d4936e1__entry__10\"></td>\n</tr>\n<tr class=\"row\" dir=\"ltr\">\n<td class=\"entry\" dir=\"ltr\" headers=\"brk1665702777359__table_d4934e1_d4935e1_d4936e1__entry__1 brk1665702777359__table_d4934e1_d4935e1_d4936e1__entry__3\">money </td>\n<td class=\"entry\" dir=\"ltr\" headers=\"brk1665702777359__table_d4934e1_d4935e1_d4936e1__entry__2 brk1665702777359__table_d4934e1_d4935e1_d4936e1__entry__4\">Y </td>\n<td class=\"entry\" dir=\"ltr\" headers=\"brk1665702777359__table_d4934e1_d4935e1_d4936e1__entry__2 brk1665702777359__table_d4934e1_d4935e1_d4936e1__entry__5\">Y </td>\n<td class=\"entry\" dir=\"ltr\" headers=\"brk1665702777359__table_d4934e1_d4935e1_d4936e1__entry__2 brk1665702777359__table_d4934e1_d4935e1_d4936e1__entry__6\">Y </td>\n<td class=\"entry\" dir=\"ltr\" headers=\"brk1665702777359__table_d4934e1_d4935e1_d4936e1__entry__2 brk1665702777359__table_d4934e1_d4935e1_d4936e1__entry__7\">Y </td>\n<td class=\"entry\" dir=\"ltr\" headers=\"brk1665702777359__table_d4934e1_d4935e1_d4936e1__entry__2 brk1665702777359__table_d4934e1_d4935e1_d4936e1__entry__8\"></td>\n<td class=\"entry\" dir=\"ltr\" headers=\"brk1665702777359__table_d4934e1_d4935e1_d4936e1__entry__2 brk1665702777359__table_d4934e1_d4935e1_d4936e1__entry__9\"></td>\n<td class=\"entry\" dir=\"ltr\" headers=\"brk1665702777359__table_d4934e1_d4935e1_d4936e1__entry__2 brk1665702777359__table_d4934e1_d4935e1_d4936e1__entry__10\"></td>\n</tr>\n<tr class=\"row\" dir=\"ltr\">\n<td class=\"entry\" dir=\"ltr\" headers=\"brk1665702777359__table_d4934e1_d4935e1_d4936e1__entry__1 brk1665702777359__table_d4934e1_d4935e1_d4936e1__entry__3\">smallmoney </td>\n<td class=\"entry\" dir=\"ltr\" headers=\"brk1665702777359__table_d4934e1_d4935e1_d4936e1__entry__2 brk1665702777359__table_d4934e1_d4935e1_d4936e1__entry__4\">Y </td>\n<td class=\"entry\" dir=\"ltr\" headers=\"brk1665702777359__table_d4934e1_d4935e1_d4936e1__entry__2 brk1665702777359__table_d4934e1_d4935e1_d4936e1__entry__5\">Y </td>\n<td class=\"entry\" dir=\"ltr\" headers=\"brk1665702777359__table_d4934e1_d4935e1_d4936e1__entry__2 brk1665702777359__table_d4934e1_d4935e1_d4936e1__entry__6\">Y </td>\n<td class=\"entry\" dir=\"ltr\" headers=\"brk1665702777359__table_d4934e1_d4935e1_d4936e1__entry__2 brk1665702777359__table_d4934e1_d4935e1_d4936e1__entry__7\">Y </td>\n<td class=\"entry\" dir=\"ltr\" headers=\"brk1665702777359__table_d4934e1_d4935e1_d4936e1__entry__2 brk1665702777359__table_d4934e1_d4935e1_d4936e1__entry__8\"></td>\n<td class=\"entry\" dir=\"ltr\" headers=\"brk1665702777359__table_d4934e1_d4935e1_d4936e1__entry__2 brk1665702777359__table_d4934e1_d4935e1_d4936e1__entry__9\"></td>\n<td class=\"entry\" dir=\"ltr\" headers=\"brk1665702777359__table_d4934e1_d4935e1_d4936e1__entry__2 brk1665702777359__table_d4934e1_d4935e1_d4936e1__entry__10\"></td>\n</tr>\n<tr class=\"row\" dir=\"ltr\">\n<td class=\"entry\" dir=\"ltr\" headers=\"brk1665702777359__table_d4934e1_d4935e1_d4936e1__entry__1 brk1665702777359__table_d4934e1_d4935e1_d4936e1__entry__3\">float </td>\n<td class=\"entry\" dir=\"ltr\" headers=\"brk1665702777359__table_d4934e1_d4935e1_d4936e1__entry__2 brk1665702777359__table_d4934e1_d4935e1_d4936e1__entry__4\">Y </td>\n<td class=\"entry\" dir=\"ltr\" headers=\"brk1665702777359__table_d4934e1_d4935e1_d4936e1__entry__2 brk1665702777359__table_d4934e1_d4935e1_d4936e1__entry__5\">Y </td>\n<td class=\"entry\" dir=\"ltr\" headers=\"brk1665702777359__table_d4934e1_d4935e1_d4936e1__entry__2 brk1665702777359__table_d4934e1_d4935e1_d4936e1__entry__6\">Y </td>\n<td class=\"entry\" dir=\"ltr\" headers=\"brk1665702777359__table_d4934e1_d4935e1_d4936e1__entry__2 brk1665702777359__table_d4934e1_d4935e1_d4936e1__entry__7\">Y </td>\n<td class=\"entry\" dir=\"ltr\" headers=\"brk1665702777359__table_d4934e1_d4935e1_d4936e1__entry__2 brk1665702777359__table_d4934e1_d4935e1_d4936e1__entry__8\"></td>\n<td class=\"entry\" dir=\"ltr\" headers=\"brk1665702777359__table_d4934e1_d4935e1_d4936e1__entry__2 brk1665702777359__table_d4934e1_d4935e1_d4936e1__entry__9\"></td>\n<td class=\"entry\" dir=\"ltr\" headers=\"brk1665702777359__table_d4934e1_d4935e1_d4936e1__entry__2 brk1665702777359__table_d4934e1_d4935e1_d4936e1__entry__10\"></td>\n</tr>\n<tr class=\"row\" dir=\"ltr\">\n<td class=\"entry\" dir=\"ltr\" headers=\"brk1665702777359__table_d4934e1_d4935e1_d4936e1__entry__1 brk1665702777359__table_d4934e1_d4935e1_d4936e1__entry__3\">real </td>\n<td class=\"entry\" dir=\"ltr\" headers=\"brk1665702777359__table_d4934e1_d4935e1_d4936e1__entry__2 brk1665702777359__table_d4934e1_d4935e1_d4936e1__entry__4\">Y </td>\n<td class=\"entry\" dir=\"ltr\" headers=\"brk1665702777359__table_d4934e1_d4935e1_d4936e1__entry__2 brk1665702777359__table_d4934e1_d4935e1_d4936e1__entry__5\">Y </td>\n<td class=\"entry\" dir=\"ltr\" headers=\"brk1665702777359__table_d4934e1_d4935e1_d4936e1__entry__2 brk1665702777359__table_d4934e1_d4935e1_d4936e1__entry__6\">Y </td>\n<td class=\"entry\" dir=\"ltr\" headers=\"brk1665702777359__table_d4934e1_d4935e1_d4936e1__entry__2 brk1665702777359__table_d4934e1_d4935e1_d4936e1__entry__7\">Y </td>\n<td class=\"entry\" dir=\"ltr\" headers=\"brk1665702777359__table_d4934e1_d4935e1_d4936e1__entry__2 brk1665702777359__table_d4934e1_d4935e1_d4936e1__entry__8\"></td>\n<td class=\"entry\" dir=\"ltr\" headers=\"brk1665702777359__table_d4934e1_d4935e1_d4936e1__entry__2 brk1665702777359__table_d4934e1_d4935e1_d4936e1__entry__9\"></td>\n<td class=\"entry\" dir=\"ltr\" headers=\"brk1665702777359__table_d4934e1_d4935e1_d4936e1__entry__2 brk1665702777359__table_d4934e1_d4935e1_d4936e1__entry__10\"></td>\n</tr>\n<tr class=\"row\" dir=\"ltr\">\n<td class=\"entry\" dir=\"ltr\" headers=\"brk1665702777359__table_d4934e1_d4935e1_d4936e1__entry__1 brk1665702777359__table_d4934e1_d4935e1_d4936e1__entry__3\">date </td>\n<td class=\"entry\" dir=\"ltr\" headers=\"brk1665702777359__table_d4934e1_d4935e1_d4936e1__entry__2 brk1665702777359__table_d4934e1_d4935e1_d4936e1__entry__4\">Y </td>\n<td class=\"entry\" dir=\"ltr\" headers=\"brk1665702777359__table_d4934e1_d4935e1_d4936e1__entry__2 brk1665702777359__table_d4934e1_d4935e1_d4936e1__entry__5\"></td>\n<td class=\"entry\" dir=\"ltr\" headers=\"brk1665702777359__table_d4934e1_d4935e1_d4936e1__entry__2 brk1665702777359__table_d4934e1_d4935e1_d4936e1__entry__6\"></td>\n<td class=\"entry\" dir=\"ltr\" headers=\"brk1665702777359__table_d4934e1_d4935e1_d4936e1__entry__2 brk1665702777359__table_d4934e1_d4935e1_d4936e1__entry__7\"></td>\n<td class=\"entry\" dir=\"ltr\" headers=\"brk1665702777359__table_d4934e1_d4935e1_d4936e1__entry__2 brk1665702777359__table_d4934e1_d4935e1_d4936e1__entry__8\">Y </td>\n<td class=\"entry\" dir=\"ltr\" headers=\"brk1665702777359__table_d4934e1_d4935e1_d4936e1__entry__2 brk1665702777359__table_d4934e1_d4935e1_d4936e1__entry__9\"></td>\n<td class=\"entry\" dir=\"ltr\" headers=\"brk1665702777359__table_d4934e1_d4935e1_d4936e1__entry__2 brk1665702777359__table_d4934e1_d4935e1_d4936e1__entry__10\">Y </td>\n</tr>\n<tr class=\"row\" dir=\"ltr\">\n<td class=\"entry\" dir=\"ltr\" headers=\"brk1665702777359__table_d4934e1_d4935e1_d4936e1__entry__1 brk1665702777359__table_d4934e1_d4935e1_d4936e1__entry__3\">datetime </td>\n<td class=\"entry\" dir=\"ltr\" headers=\"brk1665702777359__table_d4934e1_d4935e1_d4936e1__entry__2 brk1665702777359__table_d4934e1_d4935e1_d4936e1__entry__4\">Y </td>\n<td class=\"entry\" dir=\"ltr\" headers=\"brk1665702777359__table_d4934e1_d4935e1_d4936e1__entry__2 brk1665702777359__table_d4934e1_d4935e1_d4936e1__entry__5\"></td>\n<td class=\"entry\" dir=\"ltr\" headers=\"brk1665702777359__table_d4934e1_d4935e1_d4936e1__entry__2 brk1665702777359__table_d4934e1_d4935e1_d4936e1__entry__6\"></td>\n<td class=\"entry\" dir=\"ltr\" headers=\"brk1665702777359__table_d4934e1_d4935e1_d4936e1__entry__2 brk1665702777359__table_d4934e1_d4935e1_d4936e1__entry__7\"></td>\n<td class=\"entry\" dir=\"ltr\" headers=\"brk1665702777359__table_d4934e1_d4935e1_d4936e1__entry__2 brk1665702777359__table_d4934e1_d4935e1_d4936e1__entry__8\">Y </td>\n<td class=\"entry\" dir=\"ltr\" headers=\"brk1665702777359__table_d4934e1_d4935e1_d4936e1__entry__2 brk1665702777359__table_d4934e1_d4935e1_d4936e1__entry__9\"></td>\n<td class=\"entry\" dir=\"ltr\" headers=\"brk1665702777359__table_d4934e1_d4935e1_d4936e1__entry__2 brk1665702777359__table_d4934e1_d4935e1_d4936e1__entry__10\">Y </td>\n</tr>\n<tr class=\"row\" dir=\"ltr\">\n<td class=\"entry\" dir=\"ltr\" headers=\"brk1665702777359__table_d4934e1_d4935e1_d4936e1__entry__1 brk1665702777359__table_d4934e1_d4935e1_d4936e1__entry__3\">datetime2 </td>\n<td class=\"entry\" dir=\"ltr\" headers=\"brk1665702777359__table_d4934e1_d4935e1_d4936e1__entry__2 brk1665702777359__table_d4934e1_d4935e1_d4936e1__entry__4\"></td>\n<td class=\"entry\" dir=\"ltr\" headers=\"brk1665702777359__table_d4934e1_d4935e1_d4936e1__entry__2 brk1665702777359__table_d4934e1_d4935e1_d4936e1__entry__5\"></td>\n<td class=\"entry\" dir=\"ltr\" headers=\"brk1665702777359__table_d4934e1_d4935e1_d4936e1__entry__2 brk1665702777359__table_d4934e1_d4935e1_d4936e1__entry__6\"></td>\n<td class=\"entry\" dir=\"ltr\" headers=\"brk1665702777359__table_d4934e1_d4935e1_d4936e1__entry__2 brk1665702777359__table_d4934e1_d4935e1_d4936e1__entry__7\"></td>\n<td class=\"entry\" dir=\"ltr\" headers=\"brk1665702777359__table_d4934e1_d4935e1_d4936e1__entry__2 brk1665702777359__table_d4934e1_d4935e1_d4936e1__entry__8\">Y </td>\n<td class=\"entry\" dir=\"ltr\" headers=\"brk1665702777359__table_d4934e1_d4935e1_d4936e1__entry__2 brk1665702777359__table_d4934e1_d4935e1_d4936e1__entry__9\"></td>\n<td class=\"entry\" dir=\"ltr\" headers=\"brk1665702777359__table_d4934e1_d4935e1_d4936e1__entry__2 brk1665702777359__table_d4934e1_d4935e1_d4936e1__entry__10\">Y </td>\n</tr>\n<tr class=\"row\" dir=\"ltr\">\n<td class=\"entry\" dir=\"ltr\" headers=\"brk1665702777359__table_d4934e1_d4935e1_d4936e1__entry__1 brk1665702777359__table_d4934e1_d4935e1_d4936e1__entry__3\">smalldatetime </td>\n<td class=\"entry\" dir=\"ltr\" headers=\"brk1665702777359__table_d4934e1_d4935e1_d4936e1__entry__2 brk1665702777359__table_d4934e1_d4935e1_d4936e1__entry__4\"></td>\n<td class=\"entry\" dir=\"ltr\" headers=\"brk1665702777359__table_d4934e1_d4935e1_d4936e1__entry__2 brk1665702777359__table_d4934e1_d4935e1_d4936e1__entry__5\"></td>\n<td class=\"entry\" dir=\"ltr\" headers=\"brk1665702777359__table_d4934e1_d4935e1_d4936e1__entry__2 brk1665702777359__table_d4934e1_d4935e1_d4936e1__entry__6\"></td>\n<td class=\"entry\" dir=\"ltr\" headers=\"brk1665702777359__table_d4934e1_d4935e1_d4936e1__entry__2 brk1665702777359__table_d4934e1_d4935e1_d4936e1__entry__7\"></td>\n<td class=\"entry\" dir=\"ltr\" headers=\"brk1665702777359__table_d4934e1_d4935e1_d4936e1__entry__2 brk1665702777359__table_d4934e1_d4935e1_d4936e1__entry__8\">Y </td>\n<td class=\"entry\" dir=\"ltr\" headers=\"brk1665702777359__table_d4934e1_d4935e1_d4936e1__entry__2 brk1665702777359__table_d4934e1_d4935e1_d4936e1__entry__9\"></td>\n<td class=\"entry\" dir=\"ltr\" headers=\"brk1665702777359__table_d4934e1_d4935e1_d4936e1__entry__2 brk1665702777359__table_d4934e1_d4935e1_d4936e1__entry__10\">Y </td>\n</tr>\n<tr class=\"row\" dir=\"ltr\">\n<td class=\"entry\" dir=\"ltr\" headers=\"brk1665702777359__table_d4934e1_d4935e1_d4936e1__entry__1 brk1665702777359__table_d4934e1_d4935e1_d4936e1__entry__3\">datetimeoffset </td>\n<td class=\"entry\" dir=\"ltr\" headers=\"brk1665702777359__table_d4934e1_d4935e1_d4936e1__entry__2 brk1665702777359__table_d4934e1_d4935e1_d4936e1__entry__4\"></td>\n<td class=\"entry\" dir=\"ltr\" headers=\"brk1665702777359__table_d4934e1_d4935e1_d4936e1__entry__2 brk1665702777359__table_d4934e1_d4935e1_d4936e1__entry__5\"></td>\n<td class=\"entry\" dir=\"ltr\" headers=\"brk1665702777359__table_d4934e1_d4935e1_d4936e1__entry__2 brk1665702777359__table_d4934e1_d4935e1_d4936e1__entry__6\"></td>\n<td class=\"entry\" dir=\"ltr\" headers=\"brk1665702777359__table_d4934e1_d4935e1_d4936e1__entry__2 brk1665702777359__table_d4934e1_d4935e1_d4936e1__entry__7\"></td>\n<td class=\"entry\" dir=\"ltr\" headers=\"brk1665702777359__table_d4934e1_d4935e1_d4936e1__entry__2 brk1665702777359__table_d4934e1_d4935e1_d4936e1__entry__8\">Y </td>\n<td class=\"entry\" dir=\"ltr\" headers=\"brk1665702777359__table_d4934e1_d4935e1_d4936e1__entry__2 brk1665702777359__table_d4934e1_d4935e1_d4936e1__entry__9\"></td>\n<td class=\"entry\" dir=\"ltr\" headers=\"brk1665702777359__table_d4934e1_d4935e1_d4936e1__entry__2 brk1665702777359__table_d4934e1_d4935e1_d4936e1__entry__10\">Y </td>\n</tr>\n<tr class=\"row\" dir=\"ltr\">\n<td class=\"entry\" dir=\"ltr\" headers=\"brk1665702777359__table_d4934e1_d4935e1_d4936e1__entry__1 brk1665702777359__table_d4934e1_d4935e1_d4936e1__entry__3\">time </td>\n<td class=\"entry\" dir=\"ltr\" headers=\"brk1665702777359__table_d4934e1_d4935e1_d4936e1__entry__2 brk1665702777359__table_d4934e1_d4935e1_d4936e1__entry__4\">Y </td>\n<td class=\"entry\" dir=\"ltr\" headers=\"brk1665702777359__table_d4934e1_d4935e1_d4936e1__entry__2 brk1665702777359__table_d4934e1_d4935e1_d4936e1__entry__5\"></td>\n<td class=\"entry\" dir=\"ltr\" headers=\"brk1665702777359__table_d4934e1_d4935e1_d4936e1__entry__2 brk1665702777359__table_d4934e1_d4935e1_d4936e1__entry__6\"></td>\n<td class=\"entry\" dir=\"ltr\" headers=\"brk1665702777359__table_d4934e1_d4935e1_d4936e1__entry__2 brk1665702777359__table_d4934e1_d4935e1_d4936e1__entry__7\"></td>\n<td class=\"entry\" dir=\"ltr\" headers=\"brk1665702777359__table_d4934e1_d4935e1_d4936e1__entry__2 brk1665702777359__table_d4934e1_d4935e1_d4936e1__entry__8\"></td>\n<td class=\"entry\" dir=\"ltr\" headers=\"brk1665702777359__table_d4934e1_d4935e1_d4936e1__entry__2 brk1665702777359__table_d4934e1_d4935e1_d4936e1__entry__9\">Y </td>\n<td class=\"entry\" dir=\"ltr\" headers=\"brk1665702777359__table_d4934e1_d4935e1_d4936e1__entry__2 brk1665702777359__table_d4934e1_d4935e1_d4936e1__entry__10\"></td>\n</tr>\n<tr class=\"row\" dir=\"ltr\">\n<td class=\"entry\" dir=\"ltr\" headers=\"brk1665702777359__table_d4934e1_d4935e1_d4936e1__entry__1 brk1665702777359__table_d4934e1_d4935e1_d4936e1__entry__3\">binary </td>\n<td class=\"entry\" dir=\"ltr\" headers=\"brk1665702777359__table_d4934e1_d4935e1_d4936e1__entry__2 brk1665702777359__table_d4934e1_d4935e1_d4936e1__entry__4\">Y </td>\n<td class=\"entry\" dir=\"ltr\" headers=\"brk1665702777359__table_d4934e1_d4935e1_d4936e1__entry__2 brk1665702777359__table_d4934e1_d4935e1_d4936e1__entry__5\"></td>\n<td class=\"entry\" dir=\"ltr\" headers=\"brk1665702777359__table_d4934e1_d4935e1_d4936e1__entry__2 brk1665702777359__table_d4934e1_d4935e1_d4936e1__entry__6\">Y </td>\n<td class=\"entry\" dir=\"ltr\" headers=\"brk1665702777359__table_d4934e1_d4935e1_d4936e1__entry__2 brk1665702777359__table_d4934e1_d4935e1_d4936e1__entry__7\"></td>\n<td class=\"entry\" dir=\"ltr\" headers=\"brk1665702777359__table_d4934e1_d4935e1_d4936e1__entry__2 brk1665702777359__table_d4934e1_d4935e1_d4936e1__entry__8\"></td>\n<td class=\"entry\" dir=\"ltr\" headers=\"brk1665702777359__table_d4934e1_d4935e1_d4936e1__entry__2 brk1665702777359__table_d4934e1_d4935e1_d4936e1__entry__9\"></td>\n<td class=\"entry\" dir=\"ltr\" headers=\"brk1665702777359__table_d4934e1_d4935e1_d4936e1__entry__2 brk1665702777359__table_d4934e1_d4935e1_d4936e1__entry__10\"></td>\n</tr>\n<tr class=\"row\" dir=\"ltr\">\n<td class=\"entry\" dir=\"ltr\" headers=\"brk1665702777359__table_d4934e1_d4935e1_d4936e1__entry__1 brk1665702777359__table_d4934e1_d4935e1_d4936e1__entry__3\">varbinary </td>\n<td class=\"entry\" dir=\"ltr\" headers=\"brk1665702777359__table_d4934e1_d4935e1_d4936e1__entry__2 brk1665702777359__table_d4934e1_d4935e1_d4936e1__entry__4\">Y </td>\n<td class=\"entry\" dir=\"ltr\" headers=\"brk1665702777359__table_d4934e1_d4935e1_d4936e1__entry__2 brk1665702777359__table_d4934e1_d4935e1_d4936e1__entry__5\"></td>\n<td class=\"entry\" dir=\"ltr\" headers=\"brk1665702777359__table_d4934e1_d4935e1_d4936e1__entry__2 brk1665702777359__table_d4934e1_d4935e1_d4936e1__entry__6\">Y </td>\n<td class=\"entry\" dir=\"ltr\" headers=\"brk1665702777359__table_d4934e1_d4935e1_d4936e1__entry__2 brk1665702777359__table_d4934e1_d4935e1_d4936e1__entry__7\"></td>\n<td class=\"entry\" dir=\"ltr\" headers=\"brk1665702777359__table_d4934e1_d4935e1_d4936e1__entry__2 brk1665702777359__table_d4934e1_d4935e1_d4936e1__entry__8\"></td>\n<td class=\"entry\" dir=\"ltr\" headers=\"brk1665702777359__table_d4934e1_d4935e1_d4936e1__entry__2 brk1665702777359__table_d4934e1_d4935e1_d4936e1__entry__9\"></td>\n<td class=\"entry\" dir=\"ltr\" headers=\"brk1665702777359__table_d4934e1_d4935e1_d4936e1__entry__2 brk1665702777359__table_d4934e1_d4935e1_d4936e1__entry__10\"></td>\n</tr>\n</tbody></table></div>\n<div class=\"note note note_note\" id=\"brk1665702777359__note_qmz_hxl_jcc\"><span class=\"note__title\">Note:</span> The <code class=\"ph codeph\">date</code>, <code class=\"ph codeph\">time</code>,\n               <code class=\"ph codeph\">datetime2</code>, and <code class=\"ph codeph\">datetimeoffset</code> data types are only\n            supported in Microsoft SQL Server 2008.</div>\n</section>\n<section class=\"section\" id=\"brk1665702777359__section_yhp_nxl_jcc\"><h2 class=\"title sectiontitle\" id=\"d365194e1080\">IN, OUT, and INOUT Parameters </h2>\n<p class=\"p\" id=\"brk1665702777359__p_d53291e1_d53292e1_d53293e1\">All parameter data is passed to MS SQL Server as bound\n            data. To achieve optimal mapping for all parameters, MS SQL Server parameter data type\n            and operation parameter data type information is used to determine the SQL Server\n            binding data types.</p>\n</section>\n<section class=\"section\" id=\"brk1665702777359__section_okj_qxl_jcc\"><h2 class=\"title sectiontitle\" id=\"d365194e1089\">NULL Support</h2>\n<p class=\"p\" id=\"brk1665702777359__p_d53297e1_d53298e1_d53299e1\">Empty input string values are mapped to MS SQL Server\n            values as NULL values. There is one exception to this: empty Uniface boolean data types\n            are always mapped to FALSE.</p>\n</section>\n<section class=\"section\" id=\"brk1665702777359__section_spl_rxl_jcc\"><h2 class=\"title sectiontitle\" id=\"d365194e1098\">Exception Behavior </h2>\n<p class=\"p\" id=\"brk1665702777359__p_d53303e1_d53304e1_d53305e1\">The exceptions shown in the following table are\n            detected by the MSS connector:</p>\n<div class=\"table-wrap\"><table class=\"table\" count-columns=\"2\" id=\"brk1665702777359__table_d4937e1_d4938e1_d4939e1\"><caption><span class=\"table--title-label\">Table 3. </span><span class=\"title\">Exception message numbers and meanings</span></caption><colgroup><col/><col/></colgroup><thead class=\"thead\">\n<tr class=\"row\" dir=\"ltr\">\n<th class=\"entry\" dir=\"ltr\" id=\"brk1665702777359__table_d4937e1_d4938e1_d4939e1__entry__1\">$procerror </th>\n<th class=\"entry\" dir=\"ltr\" id=\"brk1665702777359__table_d4937e1_d4938e1_d4939e1__entry__2\">Meaning </th>\n</tr>\n</thead><tbody class=\"tbody\">\n<tr class=\"row\" dir=\"ltr\">\n<td class=\"entry\" dir=\"ltr\" headers=\"brk1665702777359__table_d4937e1_d4938e1_d4939e1__entry__1\">-21 </td>\n<td class=\"entry\" dir=\"ltr\" headers=\"brk1665702777359__table_d4937e1_d4938e1_d4939e1__entry__2\">Connection failure </td>\n</tr>\n<tr class=\"row\" dir=\"ltr\">\n<td class=\"entry\" dir=\"ltr\" headers=\"brk1665702777359__table_d4937e1_d4938e1_d4939e1__entry__1\">-55 </td>\n<td class=\"entry\" dir=\"ltr\" headers=\"brk1665702777359__table_d4937e1_d4938e1_d4939e1__entry__2\">Input parameters failure </td>\n</tr>\n<tr class=\"row\" dir=\"ltr\">\n<td class=\"entry\" dir=\"ltr\" headers=\"brk1665702777359__table_d4937e1_d4938e1_d4939e1__entry__1\">-56 </td>\n<td class=\"entry\" dir=\"ltr\" headers=\"brk1665702777359__table_d4937e1_d4938e1_d4939e1__entry__2\">Output parameter failure </td>\n</tr>\n<tr class=\"row\" dir=\"ltr\">\n<td class=\"entry\" dir=\"ltr\" headers=\"brk1665702777359__table_d4937e1_d4938e1_d4939e1__entry__1\">-150 </td>\n<td class=\"entry\" dir=\"ltr\" headers=\"brk1665702777359__table_d4937e1_d4938e1_d4939e1__entry__2\">Connector or MS SQL failure (for example is\n                        stored procedure not found) </td>\n</tr>\n<tr class=\"row\" dir=\"ltr\">\n<td class=\"entry\" dir=\"ltr\" headers=\"brk1665702777359__table_d4937e1_d4938e1_d4939e1__entry__1\">-166 </td>\n<td class=\"entry\" dir=\"ltr\" headers=\"brk1665702777359__table_d4937e1_d4938e1_d4939e1__entry__2\">Component signature is not stateless </td>\n</tr>\n<tr class=\"row\" dir=\"ltr\">\n<td class=\"entry\" dir=\"ltr\" headers=\"brk1665702777359__table_d4937e1_d4938e1_d4939e1__entry__1\">-1406 </td>\n<td class=\"entry\" dir=\"ltr\" headers=\"brk1665702777359__table_d4937e1_d4938e1_d4939e1__entry__2\">Memory allocation failure </td>\n</tr>\n</tbody></table></div>\n</section>\n<section class=\"section\" id=\"brk1665702777359__section_yvr_5xl_jcc\"><h2 class=\"title sectiontitle\" id=\"d365194e1190\">Example: Service Stored Procedures</h2>\n<p class=\"p\" id=\"brk1665702777359__p_d53309e1_d53310e1_d53311e1\">The following example shows a Service Stored Procedure\n            with two basic parameters. It is executed with the following <span class=\"keyword cmdname\">activate</span>\n            ProcScript statement:</p>\n<div class=\"code-toolbar\"><pre class=\"pre language-plaintext\" id=\"brk1665702777359__pre_xqh_wxl_jcc\" tabindex=\"0\"><code class=\"language-plaintext\">activate \"WORKTODO\".STR_TEST($in$, $out$)</code></pre><div class=\"toolbar\"><div class=\"toolbar-item\"><button class=\"copy-to-clipboard-button\" data-copy-state=\"copy\" type=\"button\"><span>Copy</span></button></div></div></div>\n<p class=\"p\" id=\"brk1665702777359__p_d53312e1_d53313e1_d53314e1\">The <code class=\"ph codeph\">STR_TEST</code> operation is defined in\n            a Uniface signature for the stored procedure service component, and has the following\n            parameters:</p>\n<div class=\"table-wrap\"><table class=\"table\" count-columns=\"4\" id=\"brk1665702777359__table_d4940e1_d4941e1_d4942e1\"><caption></caption><colgroup><col/><col/><col/><col/></colgroup><thead class=\"thead\">\n<tr class=\"row\" dir=\"ltr\">\n<th class=\"entry\" dir=\"ltr\" id=\"brk1665702777359__table_d4940e1_d4941e1_d4942e1__entry__1\">\n Parameter name\n </th>\n<th class=\"entry\" dir=\"ltr\" id=\"brk1665702777359__table_d4940e1_d4941e1_d4942e1__entry__2\">\n Type\n </th>\n<th class=\"entry\" dir=\"ltr\" id=\"brk1665702777359__table_d4940e1_d4941e1_d4942e1__entry__3\">\n Data type\n </th>\n<th class=\"entry\" dir=\"ltr\" id=\"brk1665702777359__table_d4940e1_d4941e1_d4942e1__entry__4\">\n Input/Output\n </th>\n</tr>\n</thead><tbody class=\"tbody\">\n<tr class=\"row\" dir=\"ltr\">\n<td class=\"entry\" dir=\"ltr\" headers=\"brk1665702777359__table_d4940e1_d4941e1_d4942e1__entry__1\">\n P1\n </td>\n<td class=\"entry\" dir=\"ltr\" headers=\"brk1665702777359__table_d4940e1_d4941e1_d4942e1__entry__2\">\n Basic\n </td>\n<td class=\"entry\" dir=\"ltr\" headers=\"brk1665702777359__table_d4940e1_d4941e1_d4942e1__entry__3\">\n String\n </td>\n<td class=\"entry\" dir=\"ltr\" headers=\"brk1665702777359__table_d4940e1_d4941e1_d4942e1__entry__4\">\n Input\n </td>\n</tr>\n<tr class=\"row\" dir=\"ltr\">\n<td class=\"entry\" dir=\"ltr\" headers=\"brk1665702777359__table_d4940e1_d4941e1_d4942e1__entry__1\">\n P2\n </td>\n<td class=\"entry\" dir=\"ltr\" headers=\"brk1665702777359__table_d4940e1_d4941e1_d4942e1__entry__2\">\n Basic\n </td>\n<td class=\"entry\" dir=\"ltr\" headers=\"brk1665702777359__table_d4940e1_d4941e1_d4942e1__entry__3\">\n String\n </td>\n<td class=\"entry\" dir=\"ltr\" headers=\"brk1665702777359__table_d4940e1_d4941e1_d4942e1__entry__4\">\n Output\n </td>\n</tr>\n</tbody></table></div>\n<p class=\"p\" id=\"brk1665702777359__p_d53315e1_d53316e1_d53317e1\">The MS SQL Server script is as follows:</p>\n<div class=\"code-toolbar\"><pre class=\"pre language-plaintext\" id=\"brk1665702777359__pre_arh_wxl_jcc\" tabindex=\"0\"><code class=\"language-plaintext\">CREATE procedure [WORKTODO].[STR_TEST] \n@in char(40), \n@out char(8000) OUTPUT \nas \nbegin \nset @out = @in \nend</code></pre><div class=\"toolbar\"><div class=\"toolbar-item\"><button class=\"copy-to-clipboard-button\" data-copy-state=\"copy\" type=\"button\"><span>Copy</span></button></div></div></div>\n</section>\n<section class=\"section\" id=\"brk1665702777359__section_xn5_yxl_jcc\"><h2 class=\"title sectiontitle\" id=\"d365194e1284\">Example: Service Stored Procedure with One Entity Parameter</h2>\n<p class=\"p\" id=\"brk1665702777359__p_d53321e1_d53322e1_d53323e1\">The second example shows a Service Stored Procedure\n            with one entity parameter. It is executed with the following <span class=\"keyword cmdname\">activate</span>\n            ProcScript statement:</p>\n<div class=\"code-toolbar\"><pre class=\"pre language-plaintext\" id=\"brk1665702777359__pre_nmp_1yl_jcc\" tabindex=\"0\"><code class=\"language-plaintext\">activate \"WORKTODO\".ENT_TEST(\"mytable.mymodel\")</code></pre><div class=\"toolbar\"><div class=\"toolbar-item\"><button class=\"copy-to-clipboard-button\" data-copy-state=\"copy\" type=\"button\"><span>Copy</span></button></div></div></div>\n<p class=\"p\" id=\"brk1665702777359__p_d53324e1_d53325e1_d53326e1\">The <code class=\"ph codeph\">ENT_TEST</code> operation has the single\n            output entity parameter shown in the table:</p>\n<div class=\"table-wrap\"><table class=\"table\" count-columns=\"4\" id=\"brk1665702777359__table_d4943e1_d4944e1_d4945e1\"><caption></caption><colgroup><col/><col/><col/><col/></colgroup><thead class=\"thead\">\n<tr class=\"row\" dir=\"ltr\">\n<th class=\"entry\" dir=\"ltr\" id=\"brk1665702777359__table_d4943e1_d4944e1_d4945e1__entry__1\">\n Parameter Name\n </th>\n<th class=\"entry\" dir=\"ltr\" id=\"brk1665702777359__table_d4943e1_d4944e1_d4945e1__entry__2\">\n Type\n </th>\n<th class=\"entry\" dir=\"ltr\" id=\"brk1665702777359__table_d4943e1_d4944e1_d4945e1__entry__3\">\n Data Type\n </th>\n<th class=\"entry\" dir=\"ltr\" id=\"brk1665702777359__table_d4943e1_d4944e1_d4945e1__entry__4\">\n Input/Output\n </th>\n</tr>\n</thead><tbody class=\"tbody\">\n<tr class=\"row\" dir=\"ltr\">\n<td class=\"entry\" dir=\"ltr\" headers=\"brk1665702777359__table_d4943e1_d4944e1_d4945e1__entry__1\">\n MYTABLE\n </td>\n<td class=\"entry\" dir=\"ltr\" headers=\"brk1665702777359__table_d4943e1_d4944e1_d4945e1__entry__2\">\n Entity\n </td>\n<td class=\"entry\" dir=\"ltr\" headers=\"brk1665702777359__table_d4943e1_d4944e1_d4945e1__entry__3\">\n —\n </td>\n<td class=\"entry\" dir=\"ltr\" headers=\"brk1665702777359__table_d4943e1_d4944e1_d4945e1__entry__4\">\n Output\n </td>\n</tr>\n</tbody></table></div>\n<div class=\"table-wrap\"><table class=\"table\" count-columns=\"3\" id=\"brk1665702777359__table_d4946e1_d4947e1_d4948e1\"><caption><span class=\"table--title-label\">Table 4. </span><span class=\"title\">MYTABLE Entity Fields</span></caption><colgroup><col/><col/><col/></colgroup><thead class=\"thead\">\n<tr class=\"row\" dir=\"ltr\">\n<th class=\"entry\" dir=\"ltr\" id=\"brk1665702777359__table_d4946e1_d4947e1_d4948e1__entry__1\">\n Field Name\n </th>\n<th class=\"entry\" dir=\"ltr\" id=\"brk1665702777359__table_d4946e1_d4947e1_d4948e1__entry__2\">\n Field Type\n </th>\n<th class=\"entry\" dir=\"ltr\" id=\"brk1665702777359__table_d4946e1_d4947e1_d4948e1__entry__3\">\n Data Type\n </th>\n</tr>\n</thead><tbody class=\"tbody\">\n<tr class=\"row\" dir=\"ltr\">\n<td class=\"entry\" dir=\"ltr\" headers=\"brk1665702777359__table_d4946e1_d4947e1_d4948e1__entry__1\">\n STR\n </td>\n<td class=\"entry\" dir=\"ltr\" headers=\"brk1665702777359__table_d4946e1_d4947e1_d4948e1__entry__2\">\n S\n </td>\n<td class=\"entry\" dir=\"ltr\" headers=\"brk1665702777359__table_d4946e1_d4947e1_d4948e1__entry__3\">\n VC40\n </td>\n</tr>\n<tr class=\"row\" dir=\"ltr\">\n<td class=\"entry\" dir=\"ltr\" headers=\"brk1665702777359__table_d4946e1_d4947e1_d4948e1__entry__1\">\n NUM\n </td>\n<td class=\"entry\" dir=\"ltr\" headers=\"brk1665702777359__table_d4946e1_d4947e1_d4948e1__entry__2\">\n N\n </td>\n<td class=\"entry\" dir=\"ltr\" headers=\"brk1665702777359__table_d4946e1_d4947e1_d4948e1__entry__3\">\n C20\n </td>\n</tr>\n</tbody></table></div>\n<p class=\"p\" id=\"brk1665702777359__p_d53327e1_d53328e1_d53329e1\">The MS SQL Server script is as follows:</p>\n<div class=\"code-toolbar\"><pre class=\"pre language-plaintext\" id=\"brk1665702777359__pre_rmp_1yl_jcc\" tabindex=\"0\"><code class=\"language-plaintext\">create procedure [WORKTODO].[ENT_TEST]\n@mytable char(40) OUTPUT \nas\nbegin \n select * from mytable; \nend </code></pre><div class=\"toolbar\"><div class=\"toolbar-item\"><button class=\"copy-to-clipboard-button\" data-copy-state=\"copy\" type=\"button\"><span>Copy</span></button></div></div></div>\n</section>\n</div>\n</article></main></article>\n</div></div><div class=\"contentPlaceholder\" style=\"height: 500px;\"><div class=\"contentContainer zDocsSideBoxes\"><div><h5 aria-level=\"5\" class=\"css-g931ng\">Related Links</h5><ul><li><a class=\"css-ettsdk\" href=\"/de-DE/bundle/uniface_104/page/aci1665702729371.html\" stylesprops=\"[object Object]\"><svg aria-hidden=\"true\" class=\"ico-related-link\"><use xlink:href=\"#ico-related-link\"></use></svg>dbowner</a><p>Specify that called stored procedures should be prefixed with the owner name.</p></li></ul></div></div></div></div><div class=\"bottomFeedback\"><div aria-labelledby=\"bottomFeedbackText\" class=\"bottomFeedbackContent\" role=\"group\"><span class=\"bottomFeedbackText\" id=\"bottomFeedbackText\">Was this topic helpful?</span><div class=\"bottomFeedbackButtonGroup\"><a data-backdrop=\"static\" data-target=\"#feedbackModal_bottom_2526197\" data-toggle=\"modal\" href=\"#\" role=\"button\" type=\"button\"><svg aria-hidden=\"true\" class=\"ico-thumbs-up\"><use xlink:href=\"#ico-thumbs-up\"></use></svg><span>Like</span></a><a data-backdrop=\"static\" data-target=\"#feedbackModal_bottom_2526197\" data-toggle=\"modal\" href=\"#\" role=\"button\" type=\"button\"><svg aria-hidden=\"true\" class=\"ico-thumbs-down\"><use xlink:href=\"#ico-thumbs-down\"></use></svg><span>Dislike</span></a></div></div></div><div style=\"position: fixed; bottom: 170px; right: 70px; cursor: pointer; transition-duration: 0.2s; transition-timing-function: linear; transition-delay: 0s; z-index: 3; opacity: 0; visibility: hidden; transition-property: opacity, visibility;\"><button aria-label=\"Scroll to top\" class=\"zDocsScrollTopBtn\" data-tooltip-content=\"Scroll to top\" data-tooltip-id=\"zDocsBackToTopToolTip\" id=\"zDocsScrollToTop\" type=\"button\"><svg aria-hidden=\"true\" class=\"ico-next\"><use xlink:href=\"#ico-next\"></use></svg></button></div></body></html>", "text": "Service Stored Procedures on Microsoft SQL Server Add to My Topics Add selected topic and subtopics Add Topic & Subtopics with topic head Add entire publication Watch Download PDF Save selected topic Save selected topic and subtopics Save entire publication Share Email Link Copy Link Feedback Last Updated Aug 13, 2024 Summarize Uniface 10.4 Service Stored Procedures on Microsoft SQL Server Service stored procedures are supported for the Microsoft SQL Server connector. The stored procedure name used for execution by Uniface is depends on the whether literal names have been defined in the signature of the Stored Procedure Component. Table 1. Component Name and Operation Name Specification Literal Component Name Literal Operation Name Stored Procedure Name Example — — UnifaceComponentName.UnifaceOperationName MY_CPT.SP1 — Specified LiteralOperationName 1 sp1 SchemaName.OperationName 2 schema.sp1 DbOwner.LiteralOperationName 3 dbo.sp1 Specified — LiteralComponentName.UnifaceOperationName sp.SP1 Specified Specified LiteralComponentName.LiteralOperationName sp.sp1 SchemaName.OperationName 2 schema.sp1 UnifaceComponentName : MY_CPT UnifaceOperationName : SP1 If LiteralOperationName does not include a schema name, the default schema of the user is used. If LiteralOperationName includes a schema name (for example, SchemaName.OperationName ), the stored procedure will be called as SchemaName.OperationName . If a literal component name is also specified, it is ignored. CAUTION: This is not recommended because it will not run on other databases connectors. If the dbowner option is specified, it is prefixed to the operation name and used instead of the default schema of the user. Parameter names are not used during the execution of stored procedures. However, their order (that is, their relative position) is used for mapping parameters. For more information, see Naming Specifications for Service Store Procedures . Database Case Sensitivity If the SQL database is defined as case-sensitive and your schema name and procedure name are not all in uppercase, you can use literal component name and literal operation name to resolve the issue. For example, a database is defined as case-sensitive, the database schema is named MySchema , and the stored procedure is named myproc1 . When defining the operation name in the Uniface signature component, you can do one of the following: Define the component literal name as: MySchema1 , and define operation literal name as myproc1 . Put all stored procedures in a shared schema and use the dbowner option to specify this schema. For more information, see dbowner . Entity Parameters When defining an operation with an entity parameter in a Uniface signature, you can define an entity parameter only as OUT or INOUT, but when creating the corresponding stored procedure in SQL Server, you must define the parameter as an OUTPUT string. Also, the name of the Uniface entity parameter must be identical to the name of the table in the database. See the example below. Data Conversions The data types of operation parameters must closely match the stored procedure parameters. If necessary, explicit and implicit conversions are used to achieve an optimal mapping for all data types. The supported parameter data type mappings for the MS SQL Server are shown in the following table. (The data type mappings shown in the table apply to both basic parameters and entity parameters.) Table 2. Uniface to Microsoft SQL Server Parameter–Data Type Mappings Uniface Parameter Data Types MS SQL Data Types String Boolean Numeric Float (L)Date (L)Time (L)Datetime char Y Y Y Y nchar Y Y Y Y varchar Y Y Y Y nvarchar Y Y Y Y decimal Y Y Y Y numeric Y Y Y Y tinyint Y Y Y Y smallint Y Y Y Y mediumint Y Y Y Y bigint Y Y Y Y int Y Y Y Y money Y Y Y Y smallmoney Y Y Y Y float Y Y Y Y real Y Y Y Y date Y Y Y datetime Y Y Y datetime2 Y Y smalldatetime Y Y datetimeoffset Y Y time Y Y binary Y Y varbinary Y Y Note: The date , time , datetime2 , and datetimeoffset data types are only supported in Microsoft SQL Server 2008. IN, OUT, and INOUT Parameters All parameter data is passed to MS SQL Server as bound data. To achieve optimal mapping for all parameters, MS SQL Server parameter data type and operation parameter data type information is used to determine the SQL Server binding data types. NULL Support Empty input string values are mapped to MS SQL Server values as NULL values. There is one exception to this: empty Uniface boolean data types are always mapped to FALSE. Exception Behavior The exceptions shown in the following table are detected by the MSS connector: Table 3. Exception message numbers and meanings $procerror Meaning -21 Connection failure -55 Input parameters failure -56 Output parameter failure -150 Connector or MS SQL failure (for example is stored procedure not found) -166 Component signature is not stateless -1406 Memory allocation failure Example: Service Stored Procedures The following example shows a Service Stored Procedure with two basic parameters. It is executed with the following activate ProcScript statement: activate \"WORKTODO\".STR_TEST($in$, $out$) Copy The STR_TEST operation is defined in a Uniface signature for the stored procedure service component, and has the following parameters: Parameter name Type Data type Input/Output P1 Basic String Input P2 Basic String Output The MS SQL Server script is as follows: CREATE procedure [WORKTODO].[STR_TEST] @in char(40), @out char(8000) OUTPUT as begin set @out = @in end Copy Example: Service Stored Procedure with One Entity Parameter The second example shows a Service Stored Procedure with one entity parameter. It is executed with the following activate ProcScript statement: activate \"WORKTODO\".ENT_TEST(\"mytable.mymodel\") Copy The ENT_TEST operation has the single output entity parameter shown in the table: Parameter Name Type Data Type Input/Output MYTABLE Entity — Output Table 4. MYTABLE Entity Fields Field Name Field Type Data Type STR S VC40 NUM N C20 The MS SQL Server script is as follows: create procedure [WORKTODO].[ENT_TEST] @mytable char(40) OUTPUT as begin select * from mytable; end Copy Related Links dbowner Specify that called stored procedures should be prefixed with the owner name. Was this topic helpful? Like Dislike"}